nse/NSE.py
nse/__init__.py
nse-1.2.9.dist-info/METADATA
nse-1.2.9.dist-info/WHEEL
nse-1.2.9.dist-info/licenses/LICENSE
nse-1.2.9.dist-info/RECORD
