Metadata-Version: 2.4
Name: nse
Version: 1.2.9
Summary: Unofficial Python Api for NSE India stock exchange
Project-URL: Bug Tracker, https://github.com/BennyThadikaran/NseIndiaApi/issues
Project-URL: Homepage, https://github.com/BennyThadikaran/NseIndiaApi
Author: Benny Thadikaran
License-File: LICENSE
Keywords: nse,nse-stock-data,stock-market-api,stock-news-api
Classifier: Intended Audience :: Developers
Classifier: Intended Audience :: Financial and Insurance Industry
Classifier: License :: OSI Approved :: GNU General Public License v3 (GPLv3)
Classifier: Natural Language :: English
Classifier: Operating System :: OS Independent
Classifier: Programming Language :: Python :: 3 :: Only
Classifier: Programming Language :: Python :: 3.8
Classifier: Programming Language :: Python :: 3.9
Classifier: Programming Language :: Python :: 3.10
Classifier: Programming Language :: Python :: 3.11
Classifier: Programming Language :: Python :: 3.12
Classifier: Programming Language :: Python :: 3.13
Classifier: Topic :: Office/Business :: Financial :: Investment
Classifier: Topic :: Software Development :: Libraries
Classifier: Topic :: Software Development :: Libraries :: Python Modules
Requires-Python: >=3.8
Requires-Dist: mthrottle>=0.0.1
Provides-Extra: dev
Requires-Dist: furo==2023.9.10; extra == 'dev'
Requires-Dist: sphinx==7.4.7; extra == 'dev'
Provides-Extra: local
Requires-Dist: requests>=2.31; extra == 'local'
Provides-Extra: server
Requires-Dist: httpx[http2]==0.28.1; extra == 'server'
